<?xml version="1.0" encoding="utf-8"?>
<odoo>
    <data>
        <template id="runbot.commit_link_details">
            <t t-call="runbot.layout" groups="base.group_user">
                <t t-foreach="commit_links" t-as="commit_link">
                    <t t-set="commit" t-value="commit_link.commit_id"/>
                    <t t-set="collapse" t-value="'collapse' + str(commit_link.id)"/>
                    <t t-set="href" t-value="'#' + collapse"/>
                    <div class="container sticky-top bg-white" style="margin-left: 50%;">
                        <p>
                            <span type="button" data-bs-toggle="collapse" t-att-data-bs-target="href" role="button" aria-expanded="true" t-att-aria-controls="collapse"><i class="fa fa-toggle-up"/></span>
                                <a t-attf-href="/runbot/commit/#{commit.id}">
                                    <span class="label" t-esc="commit.dname"/>
                                    <span t-esc="'+%s' % commit_link.diff_add" class="text-success"/>
                                    <span t-esc="'-%s' % commit_link.diff_remove" class="text-danger"/>
                                    <span class="text-info">
                                        (
                                        <span t-esc="commit_link.file_changed"/>
                                        <i class="fa fa-file"/>
                                        )
                                        <span io="behind">(
                                            <span t-esc="'%s ahead' % commit_link.base_ahead" class="text-success"/>
                                            ,
                                            <span t-esc="'%s behind' % commit_link.base_behind" class="text-danger"/>
                                        )</span>
                                    </span>
                                </a>
                                <br/>
                                Branch: <span t-esc="commit_link.branch_id.name"/><br/>
                                Version: <span t-esc="commit_link.branch_id.bundle_id.version_id.name"/><br/>
                                Base head:<span t-esc="commit_link.base_commit_id.name"/><br/>
                                Merge base:<span t-esc="commit_link.merge_base_commit_id.name"/><br/>
                        </p>
                    </div>
                    <div t-att-id="collapse" class="collapsed show" style="background-color:#223;color:CCC;padding:10px;">
                        <t t-set="diff_command" t-value="str(commit_link.merge_base_commit_id.name) +'..'+commit.name"/>
                        <i> &gt; git -C <t t-esc="commit.repo_id.name"/> show <t t-esc="diff_command"/> </i>
                        <t t-set="diff" t-value="diff_by_commit_link_ids.get(int(commit_link.id),'')"/>
                        <t t-set="commits" t-value="diff.split('\ncommit ')"/>
                        <div>
                        <t t-foreach="commits" t-as="commit_desc">
                            <t t-set="commit_name" t-value="commit_desc.split('\n', 1)[0]"/>
                            <t t-set="commit_desc" t-value="'commit ' + commit_desc"/>
                            <!--t t-set="pr" t-value="commit_desc.split(commit.repo_id.main_remote_id.short_name+'#')[1].split('\n')[0] if commit.repo_id.main_remote_id.short_name+'#' in commit_desc else None"/-->
                            <t t-set="url" t-value="'https://github.com/%s/commit/%s' % (commit.repo_id.main_remote_id.short_name, commit_name)"/>
                            <a t-att-href="url" t-att-title="commit_name" target="_blank">
                            <div style="border-bottom:25px solid #ccc;">
                                <t t-foreach="commit_desc.split('\n')" t-as="line">
                                    <t t-set="color" t-value="'#DDD'"/>
                                    <t t-set="color" t-value="'#faa'" t-if="line.startswith('-')"/>
                                    <t t-set="color" t-value="'#afa'" t-if="line.startswith('+')"/>
                                    <t t-if="line_first">
                                        <div t-esc="line" class="sticky-top bg-dark" t-attf-style="margin-right: 50%; font-family:SFMono-Regular, Menlo, Monaco, Consolas,monospace;white-space-collapse: preserve;color:{{color}}"/>
                                    </t>
                                    <t t-else="">
                                        <div t-esc="line" t-attf-style="font-family:SFMono-Regular, Menlo, Monaco, Consolas,monospace;white-space-collapse: preserve;color:{{color}}"/>
                                    </t>
                                </t>
                            </div>
                            </a>
                        </t>
                        </div>
                    </div>
                </t>
            </t>
        </template>
    </data>
</odoo>
